MANIFEST.in
README.rst
setup.py
docs/HISTORY.txt
ftw/__init__.py
ftw.gopip.egg-info/PKG-INFO
ftw.gopip.egg-info/SOURCES.txt
ftw.gopip.egg-info/dependency_links.txt
ftw.gopip.egg-info/entry_points.txt
ftw.gopip.egg-info/namespace_packages.txt
ftw.gopip.egg-info/not-zip-safe
ftw.gopip.egg-info/requires.txt
ftw.gopip.egg-info/top_level.txt
ftw/gopip/__init__.py
ftw/gopip/configure.zcml
ftw/gopip/hooks.py
ftw/gopip/ordering.py
ftw/gopip/overrides.zcml
ftw/gopip/subscribers.py
ftw/gopip/testing.py
ftw/gopip/Extensions/__init__.py
ftw/gopip/Extensions/install.py
ftw/gopip/profiles/default/metadata.xml
ftw/gopip/profiles/uninstall/.gitkeep
ftw/gopip/tests/__init__.py
ftw/gopip/tests/test_install.py
ftw/gopip/tests/test_ordering.py
ftw/gopip/tests/test_profiles.py
ftw/gopip/tests/test_uninstall.py