Metadata-Version: 1.1
Name: ftw.gopip
Version: 1.1.0
Summary: Speed up getObjPositionInParent index in Plone
Home-page: https://github.com/4teamwork/ftw.gopip
Author: 4teamwork AG
Author-email: mailto:info@4teamwork.ch
License: GPL2
Keywords: ftw gopip getObjPositionInParent
Platform: UNKNOWN
Classifier: Framework :: Plone
Classifier: Framework :: Plone :: 4.3
Classifier: Framework :: Plone :: 5.1
Classifier: License :: OSI Approved :: GNU General Public License (GPL)
Classifier: Programming Language :: Python
Classifier: Programming Language :: Python :: 2.7
Classifier: Topic :: Software Development :: Libraries :: Python Modules
